Matador-4.1.2.dist-info/DESCRIPTION.rst
Matador-4.1.2.dist-info/METADATA
Matador-4.1.2.dist-info/RECORD
Matador-4.1.2.dist-info/WHEEL
Matador-4.1.2.dist-info/entry_points.txt
Matador-4.1.2.dist-info/metadata.json
Matador-4.1.2.dist-info/top_level.txt
matador/__init__.py
matador/__main__.py
matador/git.py
matador/log.py
matador/logging.py
matador/management.py
matador/session.py
matador/zippey.py
matador/cli/__init__.py
matador/cli/abw_service.py
matador/cli/commands.py
matador/cli/decorators.py
matador/cli/sql.py
matador/cli/utils.py
matador/commands/__init__.py
matador/commands/abw_service.py
matador/commands/command.py
matador/commands/create.py
matador/commands/deploy_package.py
matador/commands/deploy_ticket.py
matador/commands/filter.py
matador/commands/run_sql_script.py
matador/commands/deployment/__init__.py
matador/commands/deployment/deploy_report.py
matador/commands/deployment/deploy_sql_script.py
matador/commands/deployment/deployment.py
matador/deployment/__init__.py
matador/deployment/deploy_report.py
matador/deployment/deploy_sql_script.py
