Metadata-Version: 2.0
Name: Matador
Version: 4.1.2
Summary: Change management for Agresso systems
Home-page: http://www.empiria.co.uk
Author: Empiria Ltd
Author-email: info@empiria.co.uk
License: The MIT License (MIT)
Platform: UNKNOWN
Classifier: Environment :: Console
Classifier: License :: OSI Approved :: MIT License
Classifier: Natural Language :: English
Requires-Python: >=3.6
Requires-Dist: click
Requires-Dist: cookiecutter
Requires-Dist: dulwich
Requires-Dist: openpyxl
Requires-Dist: pyyaml
